plone.app.linkintegrity-4.0.6-py3.12-nspkg.pth
plone/app/linkintegrity/__init__.py
plone/app/linkintegrity/configure.zcml
plone/app/linkintegrity/exceptions.py
plone/app/linkintegrity/handlers.py
plone/app/linkintegrity/interfaces.py
plone/app/linkintegrity/parser.py
plone/app/linkintegrity/retriever.py
plone/app/linkintegrity/testing.py
plone/app/linkintegrity/utils.py
plone/app/linkintegrity/browser/__init__.py
plone/app/linkintegrity/browser/configure.zcml
plone/app/linkintegrity/browser/delete_confirmation_info.pt
plone/app/linkintegrity/browser/info.py
plone/app/linkintegrity/browser/update.pt
plone/app/linkintegrity/browser/update.py
plone/app/linkintegrity/profiles/default/metadata.xml
plone/app/linkintegrity/profiles/default/ploneapplinkintegrity_default.txt
plone/app/linkintegrity/tests/__init__.py
plone/app/linkintegrity/tests/test_circular.py
plone/app/linkintegrity/tests/test_copy_paste.py
plone/app/linkintegrity/tests/test_functional.py
plone/app/linkintegrity/tests/test_handlers.py
plone/app/linkintegrity/tests/test_imagescales.py
plone/app/linkintegrity/tests/test_info.py
plone/app/linkintegrity/tests/test_references.py
plone/app/linkintegrity/tests/utils.py
plone.app.linkintegrity-4.0.6.dist-info/METADATA
plone.app.linkintegrity-4.0.6.dist-info/WHEEL
plone.app.linkintegrity-4.0.6.dist-info/entry_points.txt
plone.app.linkintegrity-4.0.6.dist-info/namespace_packages.txt
plone.app.linkintegrity-4.0.6.dist-info/top_level.txt
plone.app.linkintegrity-4.0.6.dist-info/RECORD
