Metadata-Version: 2.1
Name: plone.app.linkintegrity
Version: 4.0.6
Summary: Manage link integrity in Plone.
Home-page: https://github.com/plone/plone.app.linkintegrity
Author: Plone Foundation
Author-email: plone-developers@lists.sourceforge.net
License: GPL version 2
Keywords: link integrity plone
Platform: Any
Classifier: Development Status :: 5 - Production/Stable
Classifier: Environment :: Web Environment
Classifier: Framework :: Plone
Classifier: Framework :: Plone :: 6.0
Classifier: Framework :: Plone :: Core
Classifier: Framework :: Zope :: 5
Classifier: Intended Audience :: Other Audience
Classifier: Intended Audience :: System Administrators
Classifier: License :: OSI Approved :: GNU General Public License v2 (GPLv2)
Classifier: Operating System :: OS Independent
Classifier: Programming Language :: Python
Classifier: Programming Language :: Python :: 3.8
Classifier: Programming Language :: Python :: 3.9
Classifier: Programming Language :: Python :: 3.10
Classifier: Programming Language :: Python :: 3.11
Classifier: Topic :: Internet :: WWW/HTTP :: Site Management :: Link Checking
Requires-Python: >=3.8
Requires-Dist: setuptools
Requires-Dist: plone.app.intid
Requires-Dist: plone.app.relationfield
Requires-Dist: plone.base
Requires-Dist: plone.dexterity
Requires-Dist: Products.GenericSetup
Requires-Dist: Products.statusmessages
Requires-Dist: plone.app.textfield
Requires-Dist: plone.app.uuid
Requires-Dist: plone.registry
Requires-Dist: plone.uuid
Requires-Dist: Zope
Requires-Dist: z3c.relationfield
Requires-Dist: zc.relation
Requires-Dist: zope.intid
Requires-Dist: zope.keyreference
Provides-Extra: test
Requires-Dist: plone.app.testing ; extra == 'test'
Requires-Dist: plone.namedfile ; extra == 'test'
Requires-Dist: plone.testing ; extra == 'test'
